scrapeasaurus/__init__.py
scrapeasaurus-0.0.1.dist-info/METADATA
scrapeasaurus-0.0.1.dist-info/WHEEL
scrapeasaurus-0.0.1.dist-info/top_level.txt
scrapeasaurus-0.0.1.dist-info/RECORD
